<recipe title="Control_I_Mozzarela">
  <info author="JT-NCSU" date="13-06-09" time="16.42.07" />
  <customer name="Fox" />
  <flavorText text="Felicia the Fox took a trip to South France last year, and she wants to relive her vacation through cheese. She has given you a long list of steps required to make the perfect cheese she had that summer. Try to hit all the peaks to really send her back in time! You’ll have 1 minute and 35 seconds to finish the cheese. Bonne chance!" />
  <freshness enabled="False" delay="5" decay="60" starPenalty="2" />
  <timer usesTimer="True" timeLimit="95" />
  <elapsedTimeTweak multiplier="1" />
  <stations chop="1" cook="1" prep="1" spice="1" />
  <dish name="#Mozzarella" path="Assets/Resources/Counter/#Mozzarella.prefab" id="1">
    <step id="1" destination="Prep" visualState="0">
      <gameplay type="ElapsedTime">
        <parameters>
          <timing>
            <tweakable uncooked="2" cooked="1" burned="1" peak="75" />
            <readonly isCookable="True" isBurnable="True" hasPeakFlavor="True" />
          </timing>
        </parameters>
      </gameplay>
    </step>
    <step id="2" destination="Spice" visualState="0">
      <gameplay type="ElapsedTime">
        <parameters>
          <timing>
            <tweakable uncooked="12" cooked="6" burned="3" peak="65" />
            <readonly isCookable="True" isBurnable="True" hasPeakFlavor="True" />
          </timing>
        </parameters>
      </gameplay>
    </step>
    <step id="3" destination="Chop" visualState="0">
      <gameplay type="ElapsedTime">
        <parameters>
          <timing>
            <tweakable uncooked="5" cooked="4" burned="8" peak="25" />
            <readonly isCookable="True" isBurnable="True" hasPeakFlavor="True" />
          </timing>
        </parameters>
      </gameplay>
    </step>
    <step id="4" destination="Cook" visualState="1">
      <gameplay type="ElapsedTime">
        <parameters>
          <timing>
            <tweakable uncooked="10" cooked="10" burned="20" peak="30" />
            <readonly isCookable="True" isBurnable="True" hasPeakFlavor="True" />
          </timing>
        </parameters>
      </gameplay>
    </step>
    <step id="5" destination="Prep" visualState="1">
      <gameplay type="ElapsedTime">
        <parameters>
          <timing>
            <tweakable uncooked="2" cooked="2" burned="2" peak="50" />
            <readonly isCookable="True" isBurnable="True" hasPeakFlavor="True" />
          </timing>
        </parameters>
      </gameplay>
    </step>
    <step id="6" destination="Spice" visualState="1">
      <gameplay type="ElapsedTime">
        <parameters>
          <timing>
            <tweakable uncooked="2" cooked="1" burned="4" peak="25" />
            <readonly isCookable="True" isBurnable="True" hasPeakFlavor="True" />
          </timing>
        </parameters>
      </gameplay>
    </step>
    <step id="7" destination="Cook" visualState="2">
      <gameplay type="ElapsedTime">
        <parameters>
          <timing>
            <tweakable uncooked="9" cooked="8" burned="4" peak="75" />
            <readonly isCookable="True" isBurnable="True" hasPeakFlavor="True" />
          </timing>
        </parameters>
      </gameplay>
    </step>
    <step id="8" destination="Chop" visualState="2">
      <gameplay type="ElapsedTime">
        <parameters>
          <timing>
            <tweakable uncooked="5" cooked="12" burned="3" peak="50" />
            <readonly isCookable="True" isBurnable="True" hasPeakFlavor="True" />
          </timing>
        </parameters>
      </gameplay>
    </step>
    <step id="9" destination="Prep" visualState="2">
      <gameplay type="ElapsedTime">
        <parameters>
          <timing>
            <tweakable uncooked="12" cooked="4" peak="25" />
            <readonly isCookable="True" isBurnable="False" hasPeakFlavor="True" />
          </timing>
        </parameters>
      </gameplay>
    </step>
  </dish>
</recipe>