<recipe title="SO8_M_I_BananaNutBread">
  <info author="TW_NCSU" date="14-07-14" time="11.05.47" />
  <customer name="Walrus" />
  <flavorText text="Wanda the Walrus has had a craving for banana nut bread, and she heard that Honey’s sells it by the loaf. Wanda is here today to order a fresh, hot loaf to bring to her cousin’s house for a family gathering. You will have 1 minute and 45 seconds to make Wanda a fresh loaf. You have double cooking, prepping, spicing and chopping stations at your disposal." />
  <freshness enabled="False" delay="5" decay="60" starPenalty="2" />
  <timer usesTimer="True" timeLimit="105" />
  <elapsedTimeTweak multiplier="1" />
  <stations chop="2" cook="2" prep="2" spice="2" />
  <dish name="#Banana" path="Assets/Resources/Counter/#Banana.prefab" id="1">
    <step id="1" destination="Cook" visualState="0">
      <gameplay type="ElapsedTime">
        <parameters>
          <timing>
            <tweakable uncooked="6.00901" cooked="13.63423" burned="3.356759" />
            <readonly isCookable="True" isBurnable="True" hasPeakFlavor="False" />
          </timing>
        </parameters>
      </gameplay>
    </step>
    <step id="2" destination="Cook" visualState="0">
      <gameplay type="MiniGame">
        <parameters>
          <Chopping gameMode="proportionality" numCuts="3" />
        </parameters>
      </gameplay>
    </step>
    <step id="3" destination="Prep" visualState="0">
      <gameplay type="ElapsedTime">
        <parameters>
          <timing>
            <tweakable uncooked="3.72973" cooked="11.6036" burned="7.666667" />
            <readonly isCookable="True" isBurnable="True" hasPeakFlavor="False" />
          </timing>
        </parameters>
      </gameplay>
    </step>
    <step id="4" destination="Spice" visualState="0">
      <gameplay type="ElapsedTime">
        <parameters>
          <timing>
            <tweakable uncooked="6.962162" cooked="14.5045" burned="1.533335" />
            <readonly isCookable="True" isBurnable="True" hasPeakFlavor="False" />
          </timing>
        </parameters>
      </gameplay>
    </step>
    <step id="5" destination="Chop" visualState="1">
      <gameplay type="ElapsedTime">
        <parameters>
          <timing>
            <tweakable uncooked="3.646847" cooked="11.68649" burned="7.666666" />
            <readonly isCookable="True" isBurnable="True" hasPeakFlavor="False" />
          </timing>
        </parameters>
      </gameplay>
    </step>
  </dish>
  <dish name="#Bread" path="Assets/Resources/Counter/#Bread.prefab" id="2">
    <step id="1" destination="Prep" visualState="0">
      <gameplay type="ElapsedTime">
        <parameters>
          <timing>
            <tweakable uncooked="4.061262" cooked="11.27207" burned="7.666668" />
            <readonly isCookable="True" isBurnable="True" hasPeakFlavor="False" />
          </timing>
        </parameters>
      </gameplay>
    </step>
    <step id="2" destination="Spice" visualState="0">
      <gameplay type="ElapsedTime">
        <parameters>
          <timing>
            <tweakable uncooked="7.003604" cooked="12.22522" burned="3.771172" />
            <readonly isCookable="True" isBurnable="True" hasPeakFlavor="False" />
          </timing>
        </parameters>
      </gameplay>
    </step>
    <step id="3" destination="Prep" visualState="1">
      <gameplay type="ElapsedTime">
        <parameters>
          <timing>
            <tweakable uncooked="5.138739" cooked="10.1946" burned="7.666665" />
            <readonly isCookable="True" isBurnable="True" hasPeakFlavor="False" />
          </timing>
        </parameters>
      </gameplay>
    </step>
    <step id="4" destination="Cook" visualState="1">
      <gameplay type="ElapsedTime">
        <parameters>
          <timing>
            <tweakable uncooked="7.003604" cooked="12.30811" burned="3.688286" />
            <readonly isCookable="True" isBurnable="True" hasPeakFlavor="False" />
          </timing>
        </parameters>
      </gameplay>
    </step>
    <step id="5" destination="Chop" visualState="1">
      <gameplay type="ElapsedTime">
        <parameters>
          <timing>
            <tweakable uncooked="4.558558" cooked="10.77478" burned="7.666667" />
            <readonly isCookable="True" isBurnable="True" hasPeakFlavor="False" />
          </timing>
        </parameters>
      </gameplay>
    </step>
  </dish>
  <dish name="#Walnut" path="Assets/Resources/Counter/#Walnut.prefab" id="3">
    <step id="1" destination="Cook" visualState="0">
      <gameplay type="ElapsedTime">
        <parameters>
          <timing>
            <tweakable uncooked="5.553154" cooked="7.666679" burned="9.780167" />
            <readonly isCookable="True" isBurnable="True" hasPeakFlavor="False" />
          </timing>
        </parameters>
      </gameplay>
    </step>
    <step id="2" destination="Prep" visualState="0">
      <gameplay type="ElapsedTime">
        <parameters>
          <timing>
            <tweakable uncooked="6.920721" cooked="12.51532" burned="3.563962" />
            <readonly isCookable="True" isBurnable="True" hasPeakFlavor="False" />
          </timing>
        </parameters>
      </gameplay>
    </step>
    <step id="3" destination="Spice" visualState="0">
      <gameplay type="ElapsedTime">
        <parameters>
          <timing>
            <tweakable uncooked="4.30991" cooked="11.02342" burned="7.666667" />
            <readonly isCookable="True" isBurnable="True" hasPeakFlavor="False" />
          </timing>
        </parameters>
      </gameplay>
    </step>
    <step id="4" destination="Chop" visualState="1">
      <gameplay type="ElapsedTime">
        <parameters>
          <timing>
            <tweakable uncooked="6.87928" cooked="12.97117" burned="3.149548" />
            <readonly isCookable="True" isBurnable="True" hasPeakFlavor="False" />
          </timing>
        </parameters>
      </gameplay>
    </step>
    <step id="5" destination="Spice" visualState="1">
      <gameplay type="ElapsedTime">
        <parameters>
          <timing>
            <tweakable uncooked="5.594595" cooked="9.738739" burned="7.666666" />
            <readonly isCookable="True" isBurnable="True" hasPeakFlavor="False" />
          </timing>
        </parameters>
      </gameplay>
    </step>
  </dish>
  <dish name="#FlourDough" path="Assets/Resources/Counter/#FlourDough.prefab" id="4">
    <step id="1" destination="Spice" visualState="0">
      <gameplay type="ElapsedTime">
        <parameters>
          <timing>
            <tweakable uncooked="7.003604" cooked="8.32973" burned="7.666666" />
            <readonly isCookable="True" isBurnable="True" hasPeakFlavor="False" />
          </timing>
        </parameters>
      </gameplay>
    </step>
    <step id="2" destination="Prep" visualState="0">
      <gameplay type="ElapsedTime">
        <parameters>
          <timing>
            <tweakable uncooked="6.837839" cooked="11.06486" burned="5.097298" />
            <readonly isCookable="True" isBurnable="True" hasPeakFlavor="False" />
          </timing>
        </parameters>
      </gameplay>
    </step>
    <step id="3" destination="Spice" visualState="0">
      <gameplay type="ElapsedTime">
        <parameters>
          <timing>
            <tweakable uncooked="6.091892" cooked="9.241442" burned="7.666666" />
            <readonly isCookable="True" isBurnable="True" hasPeakFlavor="False" />
          </timing>
        </parameters>
      </gameplay>
    </step>
    <step id="4" destination="Chop" visualState="1">
      <gameplay type="MiniGame">
        <parameters>
          <Chopping gameMode="proportionality" numCuts="3" />
        </parameters>
      </gameplay>
    </step>
    <step id="5" destination="Cook" visualState="1">
      <gameplay type="ElapsedTime">
        <parameters>
          <timing>
            <tweakable uncooked="6.837838" cooked="10.07027" burned="6.09189" />
            <readonly isCookable="True" isBurnable="True" hasPeakFlavor="False" />
          </timing>
        </parameters>
      </gameplay>
    </step>
  </dish>
</recipe>