<recipe title="RD23_M_I_ApplePie">
  <info author="TR_NCSU" date="14-07-08" time="19.13.52" />
  <customer name="Goat" />
  <flavorText text="Gordon is in the mood for some apple pie! But Gordon needs your help because he's never made an apple pie before! Please help Gordon make the apple pie within the allotted time of 1 minute. Good luck, you will be great!" />
  <freshness enabled="False" delay="7" decay="60" starPenalty="1" />
  <timer usesTimer="True" timeLimit="60" />
  <elapsedTimeTweak multiplier="1" />
  <stations chop="2" cook="2" prep="2" spice="2" />
  <dish name="#Apple" path="Assets/Resources/Counter/#Apple.prefab" id="1">
    <step id="1" destination="Chop" visualState="0">
      <gameplay type="ElapsedTime">
        <parameters>
          <timing>
            <tweakable uncooked="4" cooked="4" burned="4" peak="50" />
            <readonly isCookable="True" isBurnable="True" hasPeakFlavor="True" />
          </timing>
        </parameters>
      </gameplay>
    </step>
    <step id="2" destination="Prep" visualState="1">
      <gameplay type="ElapsedTime">
        <parameters>
          <timing>
            <tweakable uncooked="3" cooked="3" burned="3" peak="50" />
            <readonly isCookable="True" isBurnable="True" hasPeakFlavor="True" />
          </timing>
        </parameters>
      </gameplay>
    </step>
    <step id="3" destination="Cook" visualState="1">
      <gameplay type="ElapsedTime">
        <parameters>
          <timing>
            <tweakable uncooked="6" cooked="6" burned="6" peak="50" />
            <readonly isCookable="True" isBurnable="True" hasPeakFlavor="True" />
          </timing>
        </parameters>
      </gameplay>
    </step>
    <step id="4" destination="Spice" visualState="1">
      <gameplay type="ElapsedTime">
        <parameters>
          <timing>
            <tweakable uncooked="4" cooked="4" burned="4" peak="50" />
            <readonly isCookable="True" isBurnable="True" hasPeakFlavor="True" />
          </timing>
        </parameters>
      </gameplay>
    </step>
    <step id="5" destination="Prep" visualState="1">
      <gameplay type="ElapsedTime">
        <parameters>
          <timing>
            <tweakable uncooked="4" cooked="4" burned="4" peak="50" />
            <readonly isCookable="True" isBurnable="True" hasPeakFlavor="True" />
          </timing>
        </parameters>
      </gameplay>
    </step>
  </dish>
  <dish name="#Pie" path="Assets/Resources/Counter/#Pie.prefab" id="2">
    <step id="1" destination="Prep" visualState="0">
      <gameplay type="ElapsedTime">
        <parameters>
          <timing>
            <tweakable uncooked="6" cooked="6" burned="6" peak="50" />
            <readonly isCookable="True" isBurnable="True" hasPeakFlavor="True" />
          </timing>
        </parameters>
      </gameplay>
    </step>
    <step id="2" destination="Cook" visualState="1">
      <gameplay type="ElapsedTime">
        <parameters>
          <timing>
            <tweakable uncooked="5" cooked="5" burned="5" peak="50" />
            <readonly isCookable="True" isBurnable="True" hasPeakFlavor="True" />
          </timing>
        </parameters>
      </gameplay>
    </step>
    <step id="3" destination="Cook" visualState="2">
      <gameplay type="ElapsedTime">
        <parameters>
          <timing>
            <tweakable uncooked="5" cooked="5" burned="5" peak="50" />
            <readonly isCookable="True" isBurnable="True" hasPeakFlavor="True" />
          </timing>
        </parameters>
      </gameplay>
    </step>
    <step id="4" destination="Prep" visualState="3">
      <gameplay type="ElapsedTime">
        <parameters>
          <timing>
            <tweakable uncooked="4" cooked="4" burned="4" peak="50" />
            <readonly isCookable="True" isBurnable="True" hasPeakFlavor="True" />
          </timing>
        </parameters>
      </gameplay>
    </step>
    <step id="5" destination="Cook" visualState="4">
      <gameplay type="ElapsedTime">
        <parameters>
          <timing>
            <tweakable uncooked="10" cooked="10" burned="10" peak="50" />
            <readonly isCookable="True" isBurnable="True" hasPeakFlavor="True" />
          </timing>
        </parameters>
      </gameplay>
    </step>
  </dish>
  <dish name="#FlourDough" path="Assets/Resources/Counter/#FlourDough.prefab" id="3">
    <step id="1" destination="Prep" visualState="0">
      <gameplay type="ElapsedTime">
        <parameters>
          <timing>
            <tweakable uncooked="6" cooked="6" burned="6" peak="50" />
            <readonly isCookable="True" isBurnable="True" hasPeakFlavor="True" />
          </timing>
        </parameters>
      </gameplay>
    </step>
    <step id="2" destination="Spice" visualState="0">
      <gameplay type="ElapsedTime">
        <parameters>
          <timing>
            <tweakable uncooked="3" cooked="3" burned="3" peak="50" />
            <readonly isCookable="True" isBurnable="True" hasPeakFlavor="True" />
          </timing>
        </parameters>
      </gameplay>
    </step>
    <step id="3" destination="Prep" visualState="0">
      <gameplay type="ElapsedTime">
        <parameters>
          <timing>
            <tweakable uncooked="4" cooked="4" burned="4" peak="50" />
            <readonly isCookable="True" isBurnable="True" hasPeakFlavor="True" />
          </timing>
        </parameters>
      </gameplay>
    </step>
    <step id="4" destination="Cook" visualState="1">
      <gameplay type="ElapsedTime">
        <parameters>
          <timing>
            <tweakable uncooked="6" cooked="6" burned="6" peak="50" />
            <readonly isCookable="True" isBurnable="True" hasPeakFlavor="True" />
          </timing>
        </parameters>
      </gameplay>
    </step>
    <step id="5" destination="Spice" visualState="1">
      <gameplay type="ElapsedTime">
        <parameters>
          <timing>
            <tweakable uncooked="3" cooked="3" burned="3" peak="50" />
            <readonly isCookable="True" isBurnable="True" hasPeakFlavor="True" />
          </timing>
        </parameters>
      </gameplay>
    </step>
  </dish>
  <dish name="#Butter" path="Assets/Resources/Counter/#Butter.prefab" id="4">
    <step id="1" destination="Chop" visualState="0">
      <gameplay type="ElapsedTime">
        <parameters>
          <timing>
            <tweakable uncooked="3" cooked="3" burned="3" peak="50" />
            <readonly isCookable="True" isBurnable="True" hasPeakFlavor="True" />
          </timing>
        </parameters>
      </gameplay>
    </step>
    <step id="2" destination="Cook" visualState="1">
      <gameplay type="ElapsedTime">
        <parameters>
          <timing>
            <tweakable uncooked="6" cooked="6" burned="6" peak="50" />
            <readonly isCookable="True" isBurnable="True" hasPeakFlavor="True" />
          </timing>
        </parameters>
      </gameplay>
    </step>
    <step id="3" destination="Chop" visualState="1">
      <gameplay type="ElapsedTime">
        <parameters>
          <timing>
            <tweakable uncooked="4" cooked="4" burned="4" peak="50" />
            <readonly isCookable="True" isBurnable="True" hasPeakFlavor="True" />
          </timing>
        </parameters>
      </gameplay>
    </step>
    <step id="4" destination="Prep" visualState="1">
      <gameplay type="ElapsedTime">
        <parameters>
          <timing>
            <tweakable uncooked="5" cooked="5" burned="5" peak="50" />
            <readonly isCookable="True" isBurnable="True" hasPeakFlavor="True" />
          </timing>
        </parameters>
      </gameplay>
    </step>
    <step id="5" destination="Spice" visualState="1">
      <gameplay type="ElapsedTime">
        <parameters>
          <timing>
            <tweakable uncooked="4" cooked="4" burned="4" peak="50" />
            <readonly isCookable="True" isBurnable="True" hasPeakFlavor="True" />
          </timing>
        </parameters>
      </gameplay>
    </step>
  </dish>
</recipe>