<recipe title="StirTutorial">
  <info author="(default)" date="13-05-20" time="17.44.26" />
  <customer name="Monkey" />
  <flavorText text="(intro text)" />
  <freshness enabled="False" delay="5" decay="60" starPenalty="2" />
  <timer usesTimer="False" timeLimit="0" />
  <elapsedTimeTweak multiplier="1" />
  <stations chop="0" cook="1" prep="0" spice="0" />
  <dish name="#Carrot" path="Assets/Resources/Counter/#Carrot.prefab" id="1">
    <step id="1" destination="Cook" visualState="1">
      <gameplay type="MiniGame">
        <parameters>
          <Stirring />
        </parameters>
      </gameplay>
    </step>
  </dish>
</recipe>